better_instagram/__init__.py
better_instagram/better_instagram.py
better_instagram-0.0.1.dist-info/LICENSE
better_instagram-0.0.1.dist-info/METADATA
better_instagram-0.0.1.dist-info/WHEEL
better_instagram-0.0.1.dist-info/top_level.txt
better_instagram-0.0.1.dist-info/RECORD
