Metadata-Version: 2.1
Name: better-instagram
Version: 0.0.1
Summary: For accessing info of both public and private instagram accounts
Home-page: https://github.com/oyas4572/better_instagram
Author: oyas
Author-email: third4572@gmail.com
License: UNKNOWN
Platform: UNKNOWN
Classifier: Programming Language :: Python :: 3
Classifier: License :: OSI Approved :: MIT License
Classifier: Operating System :: OS Independent
Requires-Python: >=3.7
License-File: LICENSE
